arts/__init__.py
arts/skybox/README.md
arts/skybox/README.tar
arts/skybox/update_hashes.py
arts/skybox/update_hashes.tar
arts/skybox/files/代码/github_apps/2026年/github_apps_20260129.tar.hash.yaml
arts/skybox/files/代码/github_apps/2026年以前/english_words_20231210_独家版权单词11679个.tar.hash.yaml
arts/skybox/files/代码/github_apps/2026年以前/english_words_20250920_上传单词11667个_含音频.tar.hash.yaml
arts/skybox/files/代码/github_apps/2026年以前/english_words_20251130_移除音频、添加站点图标.tar.hash.yaml
arts/skybox/files/代码/github_apps/2026年以前/huango_v1.0_git仓库+源码+二进制.tar.hash.yaml
arts/skybox/files/代码/github_apps/2026年以前/huango_v1.0_二进制.tar.hash.yaml
arts/skybox/files/代码/github_apps/2026年以前/huango_v2.0_git仓库+源码+二进制+pypi仓库.tar.hash.yaml
arts/skybox/files/代码/github_apps/2026年以前/huango_v2.0_二进制.tar.hash.yaml
arts/skybox/files/代码/github_arts/2026年/github_arts_20260129.tar.hash.yaml
arts/skybox/files/代码/github_arts/2026年以前/github_arts_20250330.tar.hash.yaml
arts/skybox/files/代码/github_arts/2026年以前/github_arts_20251002.tar.hash.yaml
arts/skybox/files/代码/github_arts/2026年以前/github_arts_20251121.tar.hash.yaml
arts/skybox/files/代码/github_arts/2026年以前/github_arts_20251128_勿删，已有多名开发者知晓.tar.hash.yaml
arts/skybox/files/代码/github_arts/2026年以前/github_arts_20251209_完整版，文件+git历史.tar.hash.yaml
arts/skybox/files/代码/skk/skk_20251120.tar.hash.yaml
arts/skybox/files/代码/skk/skk_20260129.tar.hash.yaml
arts/skybox/files/代码/study_vortex/2026年以前/study_vortex_20231209_v1.0_英语_演示.tar.hash.yaml
arts/skybox/files/代码/study_vortex/2026年以前/study_vortex_20231211_v1.0.1_英语_源码.tar.hash.yaml
arts/skybox/files/代码/study_vortex/2026年以前/study_vortex_20240619_v1.1_多领域_宣传片.tar.hash.yaml
arts/skybox/files/代码/study_vortex/2026年以前/study_vortex_20240729_v1.1.1_多领域_源码.tar.hash.yaml
arts/skybox/files/代码/study_vortex/2026年以前/study_vortex_20240820_v1.3_支持富文本知识库_二进制.tar.hash.yaml
arts/skybox/files/代码/study_vortex/2026年以前/study_vortex_20251107_v1.3.1_简化_源码.tar.hash.yaml
arts/skybox/files/代码/wss/wss_20231220.tar.hash.yaml
arts-2026.1.29.dist-info/WHEEL
arts-2026.1.29.dist-info/METADATA
arts-2026.1.29.dist-info/RECORD
