Metadata-Version: 2.4
Name: arts
Version: 2026.1.29
Summary: 一个基于正则表达式的文件/文件夹路径查找工具
Author-email: 许灿标 <canbiaoxu@outlook.com>
Requires-Python: >=3.12
Requires-Dist: tornado
